MANIFEST.in
README.rst
TODO
setup.py
wsconfig.py
tests/__init__.py
tests/test_applying.py
tests/test_parsing.py
tests/test_plugins.py
wsconfig/__init__.py
wsconfig/parsing.py
wsconfig/plugins.py
wsconfig/script.py
wsconfig.egg-info/PKG-INFO
wsconfig.egg-info/SOURCES.txt
wsconfig.egg-info/dependency_links.txt
wsconfig.egg-info/entry_points.txt
wsconfig.egg-info/not-zip-safe
wsconfig.egg-info/requires.txt
wsconfig.egg-info/top_level.txt