Metadata-Version: 1.0
Name: wsconfig
Version: 0.2
Summary: A tiny utility to automatize setting up a new workstation; linking config files and installing packages. 
Home-page: http://github.com/miracle2k/wsconfig
Author: Michael Elsdörfer
Author-email: michael@elsdoerfer.com
License: BSD
Platform: UNKNOWN
Classifier: License :: OSI Approved :: BSD License
